weld/__init__.py
weld/__main__.py
weld/cli.py
weld/completions.py
weld/config.py
weld/constants.py
weld/logging.py
weld/output.py
weld/py.typed
weld/validation.py
weld/commands/__init__.py
weld/commands/commit.py
weld/commands/discover.py
weld/commands/doc_review.py
weld/commands/doctor.py
weld/commands/implement.py
weld/commands/init.py
weld/commands/interview.py
weld/commands/plan.py
weld/commands/prompt.py
weld/commands/research.py
weld/core/__init__.py
weld/core/discover_engine.py
weld/core/doc_review_engine.py
weld/core/history.py
weld/core/interview_engine.py
weld/core/plan_parser.py
weld/core/prompt_customizer.py
weld/core/validators.py
weld/core/weld_dir.py
weld/models/__init__.py
weld/models/discover.py
weld/models/issues.py
weld/models/session.py
weld/services/__init__.py
weld/services/claude.py
weld/services/filesystem.py
weld/services/gist_uploader.py
weld/services/git.py
weld/services/session_detector.py
weld/services/session_tracker.py
weld/services/transcript_renderer.py
weld/services/transcripts.py
weld/telegram/__init__.py
weld/telegram/auth.py
weld/telegram/bot.py
weld/telegram/cli.py
weld/telegram/config.py
weld/telegram/errors.py
weld/telegram/files.py
weld/telegram/format.py
weld/telegram/queue.py
weld/telegram/runner.py
weld/telegram/state.py
weld_cli-0.13.0.dist-info/METADATA
weld_cli-0.13.0.dist-info/WHEEL
weld_cli-0.13.0.dist-info/entry_points.txt
weld_cli-0.13.0.dist-info/licenses/LICENSE
weld_cli-0.13.0.dist-info/RECORD
