Metadata-Version: 2.4
Name: weld-cli
Version: 0.13.0
Summary: Human-in-the-loop coding harness: plan, review, iterate, commit with transcript provenance
Project-URL: Homepage, https://github.com/ametel01/weld-cli
Project-URL: Documentation, https://ametel01.github.io/weld-cli/
Project-URL: Repository, https://github.com/ametel01/weld-cli.git
Project-URL: Issues, https://github.com/ametel01/weld-cli/issues
Project-URL: Changelog, https://github.com/ametel01/weld-cli/blob/master/CHANGELOG.md
Author: Alex Metelli
License-Expression: Apache-2.0
License-File: LICENSE
Classifier: Development Status :: 4 - Beta
Classifier: Environment :: Console
Classifier: Intended Audience :: Developers
Classifier: License :: OSI Approved :: Apache Software License
Classifier: Operating System :: OS Independent
Classifier: Programming Language :: Python :: 3
Classifier: Programming Language :: Python :: 3.11
Classifier: Programming Language :: Python :: 3.12
Classifier: Programming Language :: Python :: 3.13
Classifier: Topic :: Software Development :: Quality Assurance
Classifier: Topic :: Software Development :: Version Control :: Git
Classifier: Typing :: Typed
Requires-Python: >=3.11
Requires-Dist: aiogram>=3.22
Requires-Dist: aiosqlite>=0.19
Requires-Dist: pathspec>=0.12
Requires-Dist: pydantic>=2.6
Requires-Dist: rich>=13.7
Requires-Dist: simple-term-menu>=1.6
Requires-Dist: tomli-w>=1.0
Requires-Dist: typer>=0.12
